pytest_stepfunctions/__init__.py
pytest_stepfunctions/plugin.py
pytest_stepfunctions/services/__init__.py
pytest_stepfunctions/services/aws_lambda.py
pytest_stepfunctions-0.1.1.dist-info/LICENSE
pytest_stepfunctions-0.1.1.dist-info/METADATA
pytest_stepfunctions-0.1.1.dist-info/WHEEL
pytest_stepfunctions-0.1.1.dist-info/entry_points.txt
pytest_stepfunctions-0.1.1.dist-info/top_level.txt
pytest_stepfunctions-0.1.1.dist-info/RECORD
