Metadata-Version: 2.1
Name: pytest-stepfunctions
Version: 0.1.1
Summary: A small description
Home-page: https://github.com/chehsunliu/pytest-stepfunctions
Author: Che-Hsun Liu
Author-email: chehsunliu@gmail.com
License: MIT
Platform: UNKNOWN
Classifier: Operating System :: OS Independent
Classifier: License :: OSI Approved :: MIT License
Classifier: Intended Audience :: Developers
Classifier: Development Status :: 4 - Beta
Classifier: Framework :: Pytest
Classifier: Programming Language :: Python :: 3.6
Classifier: Programming Language :: Python :: 3.7
Classifier: Programming Language :: Python :: 3.8
Classifier: Topic :: Software Development :: Quality Assurance
Classifier: Topic :: Software Development :: Testing
Requires-Python: >=3.6
Requires-Dist: pytest
